{
  "timestamp": "2025-10-05T12:05:15.592140",
  "total_rfqs": 2,
  "cities_scraped": 2,
  "success_count": 2,
  "failed_count": 0,
  "alerts": [],
  "cities": {
    "Town of Florence": {
      "rfq_count": 1,
      "status": "success",
      "error": null,
      "strategy_used": "div_rows"
    },
    "Town of Queen Creek": {
      "rfq_count": 1,
      "status": "success",
      "error": null,
      "strategy_used": "div_rows"
    }
  },
  "has_critical_alerts": false,
  "has_warnings": false
}